{
  "mcpServers": {
    "111": {
      "type": "stdio",
      "command": "npx",
      "args": [
        "@playwright/mcp@latest",
        "--headless"
      ]
    },
    "222": {
      "type": "stdio",
      "command": "npx",
      "args": [
        "@playwright/mcp@latest",
        "--headless"
      ]
    },
    "412412": {
      "type": "stdio",
      "description": "不错",
      "command": "npx",
      "args": [
        "@playwright/mcp@latest",
        "--headless"
      ]
    },
    "4234234": {
      "type": "stdio",
      "command": "npx",
      "args": [
        "@playwright/mcp@latest",
        "--headless"
      ]
    },
    "amap": {
      "command": "npx",
      "description": "高德地图 MCP 服务",
      "args": [
        "-y",
        "@amap/amap-maps-mcp-server"
      ],
      "env": {
        "AMAP_MAPS_API_KEY": "your-api-key"
      },
      "tools": {
        "amap-maps_regeocode": {
          "enabled": true
        }
      },
      "enabled": true
    },
    "playwright": {
      "command": "npx",
      "description": "Playwright MCP 服务",
      "args": [
        "@playwright/mcp@latest",
        "--headless"
      ],
      "enabled": true
    },
    "fetch": {
      "command": "uvx",
      "description": "Fetch MCP 服务",
      "args": [
        "mcp-server-fetch"
      ],
      "enabled": false
    },
    "slack": {
      "type": "stdio",
      "command": "npx",
      "args": [
        "-y",
        "@modelcontextprotocol/server-slack"
      ],
      "env": {
        "SLACK_BOT_TOKEN": "your-bot-token",
        "SLACK_TEAM_ID": "your-team-id"
      }
    },
    "text": {
      "type": "stdio",
      "description": "内容",
      "command": "npx",
      "args": [
        "@playwright/mcp@latest",
        "--headless"
      ]
    },
    "npx-test": {
      "type": "stdio",
      "command": "npx",
      "args": [
        "@playwright/mcp@latest",
        "--headless"
      ]
    },
    "npx2-test": {
      "type": "stdio",
      "command": "npx",
      "args": [
        "-y",
        "@modelcontextprotocol/server-slack"
      ],
      "env": {
        "SLACK_BOT_TOKEN": "your-bot-token",
        "SLACK_TEAM_ID": "your-team-id"
      },
      "enabled": true
    },
    "423sdfs": {
      "type": "stdio",
      "command": "npx",
      "args": [
        "@playwright/mcp@latest",
        "--headless"
      ]
    }
  },
  "users": [
    {
      "username": "admin",
      "password": "$2b$10$Vt7krIvjNgyN67LXqly0uOcTpN0LI55cYRbcKC71pUDAP0nJ7RPa.",
      "isAdmin": true
    }
  ]
}